teamspeak_bot/__init__.py
teamspeak_bot/__main__.py
teamspeak_bot/bot.py
teamspeak_bot/common.py
teamspeak_bot/config.py
teamspeak_bot/logging.py
teamspeak_bot/py.typed
teamspeak_bot/plugins/__init__.py
teamspeak_bot/plugins/admin.py
teamspeak_bot/plugins/afk_mover.py
teamspeak_bot/plugins/announce.py
teamspeak_bot/plugins/banned_names.py
teamspeak_bot/plugins/error_events.py
teamspeak_bot/plugins/fun.py
teamspeak_bot/plugins/greeter.py
teamspeak_bot/plugins/jail.py
teamspeak_bot/plugins/jokes.py
teamspeak_bot/plugins/notify.py
teamspeak_bot/plugins/plugin_config.py
teamspeak_bot/utils/__init__.py
teamspeak_bot/utils/cache.py
teamspeak_bot/utils/checks.py
teamspeak_bot/utils/find.py
teamspeak_bot/utils/formatters.py
teamspeak_bot/utils/get.py
teamspeak_bot/utils/merge.py
teamspeak_bot/utils/parsers.py
teamspeak_bot/utils/try_.py
teamspeak_bot-0.3.3.dist-info/licenses/LICENSE
teamspeak_bot-0.3.3.dist-info/METADATA
teamspeak_bot-0.3.3.dist-info/WHEEL
teamspeak_bot-0.3.3.dist-info/entry_points.txt
teamspeak_bot-0.3.3.dist-info/top_level.txt
teamspeak_bot-0.3.3.dist-info/RECORD
