Metadata-Version: 2.4
Name: teamspeak_bot
Version: 0.3.3
Summary: Python TeamSpeak bot using TSBot framework
Author: jykob
License: MIT License
Project-URL: repository, https://github.com/jykob/teamspeak-bot
Classifier: Framework :: AsyncIO
Classifier: License :: OSI Approved :: MIT License
Classifier: Operating System :: OS Independent
Classifier: Programming Language :: Python :: 3
Classifier: Programming Language :: Python :: 3 :: Only
Classifier: Programming Language :: Python :: 3.12
Requires-Python: >=3.12
License-File: LICENSE
Requires-Dist: tsbot==1.7.1
Requires-Dist: tsformatter==0.2.2
Requires-Dist: result==0.17.0
Requires-Dist: httpx==0.27.2
Provides-Extra: dev
Requires-Dist: ruff>=0.4.4; extra == "dev"
Requires-Dist: pyright>=1.1.362; extra == "dev"
Requires-Dist: python-dotenv==1.0.1; extra == "dev"
Dynamic: license-file
